dealcloud_sdk/__init__.py
dealcloud_sdk/base/__init__.py
dealcloud_sdk/base/dealcloud_base.py
dealcloud_sdk/constants/__init__.py
dealcloud_sdk/constants/auth.py
dealcloud_sdk/constants/data.py
dealcloud_sdk/constants/env_var_names.py
dealcloud_sdk/constants/field_types.py
dealcloud_sdk/constants/request.py
dealcloud_sdk/data/__init__.py
dealcloud_sdk/data/dealcloud_data.py
dealcloud_sdk/dealcloud.py
dealcloud_sdk/factories/__init__.py
dealcloud_sdk/factories/from_env.py
dealcloud_sdk/factories/from_json.py
dealcloud_sdk/factories/from_yaml.py
dealcloud_sdk/models/__init__.py
dealcloud_sdk/models/auth.py
dealcloud_sdk/models/data.py
dealcloud_sdk/models/factory_models.py
dealcloud_sdk/models/schema.py
dealcloud_sdk/py.typed
dealcloud_sdk/schema/__init__.py
dealcloud_sdk/schema/dealcloud_schema.py
dealcloud_sdk/utils/__init__.py
dealcloud_sdk/utils/common_argument_parse.py
dealcloud_sdk/utils/data_utils.py
dealcloud_sdk/utils/get_key.py
dealcloud_sdk/utils/process_response_errors.py
dealcloud_sdk/utils/request_retry.py
dealcloud_sdk/utils/resolve_references.py
dealcloud_sdk/utils/validation.py
dealcloud_sdk-0.1.9.dist-info/LICENSE
dealcloud_sdk-0.1.9.dist-info/METADATA
dealcloud_sdk-0.1.9.dist-info/WHEEL
dealcloud_sdk-0.1.9.dist-info/RECORD
