Metadata-Version: 2.1
Name: dealcloud_sdk
Version: 0.1.9
Summary: DealCloud SDK is a wrapper around the DealCloud API, designed to assist clients and partners to build on top of our platform quickly and easily.
License: Intapp License for Supplemental Software
Author: Intapp
Author-email: support@dealcloud.com
Requires-Python: >=3.9,<3.15
Classifier: License :: Other/Proprietary License
Classifier: Programming Language :: Python :: 3
Classifier: Programming Language :: Python :: 3.9
Classifier: Programming Language :: Python :: 3.10
Classifier: Programming Language :: Python :: 3.11
Classifier: Programming Language :: Python :: 3.12
Classifier: Programming Language :: Python :: 3.13
Requires-Dist: pandas (>=2.1.1,<3.0.0)
Requires-Dist: pydantic (>=2.4.2,<3.0.0)
Requires-Dist: python-benedict[yaml] (>=0.33.0,<0.34.0)
Requires-Dist: requests (>=2.31.0,<3.0.0)
Requires-Dist: requests-futures (>=1.0.1,<2.0.0)
